{
  "id": 1199,
  "vertexCount": 124,
  "vertexX": [
    20,
    11,
    11,
    20,
    28,
    34,
    20,
    6,
    19,
    19,
    19,
    6,
    20,
    28,
    19,
    19,
    31,
    20,
    8,
    34,
    32,
    21,
    7,
    19,
    55,
    5,
    10,
    54,
    55,
    56,
    5,
    -14,
    -11,
    -11,
    10,
    -51,
    -52,
    -52,
    -31,
    -51,
    -12,
    5,
    5,
    -31,
    -50,
    -52,
    -52,
    -12,
    8,
    54,
    55,
    53,
    55,
    54,
    10,
    7,
    54,
    54,
    8,
    -21,
    -32,
    -32,
    7,
    -50,
    -50,
    -52,
    -22,
    -52,
    -14,
    -52,
    8,
    54,
    5,
    10,
    53,
    55,
    55,
    5,
    -14,
    -11,
    -11,
    10,
    -51,
    -52,
    -52,
    -14,
    -52,
    42,
    42,
    30,
    30,
    42,
    42,
    30,
    30,
    42,
    42,
    30,
    30,
    42,
    42,
    30,
    30,
    -27,
    -27,
    -39,
    -39,
    -27,
    -27,
    -39,
    -39,
    -27,
    -27,
    -39,
    -39,
    -27,
    -27,
    -39,
    -39,
    20,
    20,
    20,
    20,
    20
  ],
  "vertexY": [
    -108,
    -108,
    -78,
    -78,
    -108,
    -110,
    -110,
    -110,
    -108,
    -78,
    -76,
    -76,
    -76,
    -78,
    -110,
    -114,
    -114,
    -114,
    -114,
    -76,
    -72,
    -72,
    -72,
    -72,
    -73,
    -73,
    -73,
    -73,
    -64,
    -64,
    -64,
    -73,
    -73,
    -64,
    -64,
    -73,
    -73,
    -64,
    -73,
    -73,
    -73,
    -73,
    -64,
    -64,
    -73,
    -64,
    -64,
    -64,
    -73,
    -73,
    -64,
    -73,
    -64,
    -73,
    -73,
    -73,
    -64,
    -64,
    -64,
    -73,
    -73,
    -64,
    -64,
    -73,
    -73,
    -64,
    -64,
    -64,
    -64,
    -64,
    -64,
    -73,
    -73,
    -73,
    -73,
    -64,
    -64,
    -64,
    -73,
    -73,
    -64,
    -64,
    -73,
    -73,
    -64,
    -64,
    -64,
    -64,
    -64,
    -64,
    -64,
    0,
    0,
    0,
    0,
    -64,
    -64,
    -64,
    -64,
    0,
    0,
    0,
    0,
    -64,
    -64,
    -64,
    -64,
    0,
    0,
    0,
    0,
    -64,
    -64,
    -64,
    -64,
    0,
    0,
    0,
    0,
    -108,
    -108,
    -108,
    -108,
    -108
  ],
  "vertexZ": [
    22,
    30,
    30,
    22,
    31,
    31,
    16,
    29,
    39,
    39,
    44,
    29,
    16,
    31,
    44,
    41,
    31,
    19,
    30,
    31,
    32,
    43,
    28,
    17,
    1,
    1,
    -22,
    -21,
    -20,
    1,
    1,
    1,
    -21,
    -21,
    -22,
    1,
    -21,
    -20,
    24,
    2,
    2,
    26,
    26,
    24,
    23,
    23,
    3,
    2,
    2,
    24,
    23,
    3,
    4,
    50,
    51,
    27,
    27,
    51,
    52,
    50,
    26,
    26,
    28,
    51,
    24,
    25,
    52,
    51,
    1,
    1,
    2,
    -23,
    -23,
    -51,
    -50,
    -49,
    -23,
    -23,
    -23,
    -51,
    -51,
    -51,
    -23,
    -51,
    -50,
    -23,
    -23,
    -40,
    -28,
    -28,
    -40,
    -40,
    -28,
    -28,
    -40,
    32,
    44,
    44,
    32,
    32,
    44,
    44,
    32,
    -40,
    -28,
    -28,
    -40,
    -40,
    -28,
    -28,
    -40,
    32,
    44,
    44,
    32,
    32,
    44,
    44,
    32,
    22,
    22,
    22,
    22,
    22
  ],
  "vertexNormals": [
    {
      "x": -58,
      "y": 699,
      "z": -776,
      "magnitude": 6
    },
    {
      "x": -801,
      "y": 681,
      "z": 82,
      "magnitude": 6
    },
    {
      "x": -811,
      "y": -671,
      "z": -117,
      "magnitude": 6
    },
    {
      "x": 151,
      "y": -696,
      "z": -770,
      "magnitude": 6
    },
    {
      "x": 786,
      "y": 688,
      "z": -40,
      "magnitude": 6
    },
    {
      "x": 695,
      "y": 334,
      "z": 134,
      "magnitude": 6
    },
    {
      "x": 117,
      "y": 336,
      "z": -709,
      "magnitude": 6
    },
    {
      "x": -777,
      "y": 370,
      "z": -70,
      "magnitude": 6
    },
    {
      "x": 24,
      "y": 658,
      "z": 822,
      "magnitude": 6
    },
    {
      "x": -156,
      "y": -681,
      "z": 797,
      "magnitude": 6
    },
    {
      "x": 48,
      "y": -554,
      "z": 788,
      "magnitude": 6
    },
    {
      "x": -773,
      "y": -478,
      "z": 52,
      "magnitude": 6
    },
    {
      "x": -80,
      "y": -614,
      "z": -768,
      "magnitude": 6
    },
    {
      "x": 772,
      "y": -697,
      "z": 148,
      "magnitude": 6
    },
    {
      "x": -148,
      "y": 373,
      "z": 757,
      "magnitude": 6
    },
    {
      "x": 134,
      "y": -613,
      "z": 506,
      "magnitude": 4
    },
    {
      "x": 481,
      "y": -861,
      "z": -130,
      "magnitude": 5
    },
    {
      "x": -139,
      "y": -613,
      "z": -486,
      "magnitude": 4
    },
    {
      "x": -503,
      "y": -804,
      "z": 156,
      "magnitude": 5
    },
    {
      "x": 746,
      "y": -452,
      "z": -15,
      "magnitude": 6
    },
    {
      "x": 514,
      "y": 113,
      "z": 223,
      "magnitude": 3
    },
    {
      "x": -168,
      "y": 163,
      "z": 489,
      "magnitude": 3
    },
    {
      "x": -524,
      "y": 85,
      "z": -213,
      "magnitude": 3
    },
    {
      "x": 173,
      "y": 210,
      "z": -500,
      "magnitude": 3
    },
    {
      "x": 508,
      "y": -567,
      "z": 233,
      "magnitude": 5
    },
    {
      "x": 0,
      "y": -768,
      "z": 768,
      "magnitude": 6
    },
    {
      "x": -19,
      "y": -768,
      "z": -768,
      "magnitude": 6
    },
    {
      "x": 270,
      "y": -256,
      "z": -521,
      "magnitude": 4
    },
    {
      "x": 519,
      "y": -28,
      "z": -277,
      "magnitude": 3
    },
    {
      "x": 254,
      "y": -28,
      "z": 500,
      "magnitude": 3
    },
    {
      "x": 0,
      "y": 0,
      "z": 768,
      "magnitude": 3
    },
    {
      "x": 0,
      "y": -768,
      "z": 768,
      "magnitude": 6
    },
    {
      "x": -18,
      "y": -740,
      "z": -766,
      "magnitude": 6
    },
    {
      "x": -30,
      "y": 0,
      "z": -768,
      "magnitude": 3
    },
    {
      "x": 4,
      "y": 27,
      "z": -766,
      "magnitude": 3
    },
    {
      "x": -254,
      "y": -284,
      "z": 523,
      "magnitude": 4
    },
    {
      "x": -510,
      "y": -512,
      "z": -243,
      "magnitude": 5
    },
    {
      "x": -262,
      "y": 28,
      "z": -510,
      "magnitude": 3
    },
    {
      "x": -41,
      "y": -768,
      "z": 768,
      "magnitude": 6
    },
    {
      "x": -504,
      "y": -567,
      "z": -243,
      "magnitude": 5
    },
    {
      "x": -6,
      "y": -740,
      "z": -766,
      "magnitude": 6
    },
    {
      "x": 11,
      "y": -741,
      "z": 766,
      "magnitude": 6
    },
    {
      "x": -13,
      "y": 0,
      "z": 768,
      "magnitude": 3
    },
    {
      "x": -39,
      "y": -2,
      "z": 768,
      "magnitude": 3
    },
    {
      "x": -275,
      "y": -313,
      "z": 523,
      "magnitude": 4
    },
    {
      "x": -516,
      "y": -85,
      "z": 267,
      "magnitude": 3
    },
    {
      "x": -260,
      "y": 0,
      "z": -510,
      "magnitude": 3
    },
    {
      "x": -6,
      "y": 0,
      "z": -768,
      "magnitude": 3
    },
    {
      "x": 5,
      "y": -768,
      "z": -768,
      "magnitude": 6
    },
    {
      "x": 749,
      "y": -714,
      "z": -254,
      "magnitude": 9
    },
    {
      "x": 279,
      "y": -1,
      "z": 510,
      "magnitude": 3
    },
    {
      "x": 265,
      "y": -285,
      "z": -521,
      "magnitude": 4
    },
    {
      "x": 514,
      "y": -57,
      "z": -265,
      "magnitude": 3
    },
    {
      "x": 517,
      "y": -540,
      "z": 254,
      "magnitude": 5
    },
    {
      "x": 2,
      "y": -853,
      "z": 762,
      "magnitude": 6
    },
    {
      "x": 3,
      "y": -712,
      "z": -764,
      "magnitude": 6
    },
    {
      "x": 507,
      "y": 81,
      "z": -243,
      "magnitude": 3
    },
    {
      "x": 266,
      "y": -55,
      "z": 508,
      "magnitude": 3
    },
    {
      "x": -3,
      "y": -112,
      "z": 758,
      "magnitude": 3
    },
    {
      "x": 0,
      "y": -907,
      "z": 754,
      "magnitude": 6
    },
    {
      "x": 46,
      "y": -734,
      "z": -764,
      "magnitude": 6
    },
    {
      "x": 31,
      "y": 28,
      "z": -766,
      "magnitude": 3
    },
    {
      "x": -8,
      "y": 137,
      "z": -751,
      "magnitude": 3
    },
    {
      "x": -250,
      "y": -366,
      "z": 506,
      "magnitude": 4
    },
    {
      "x": -472,
      "y": -588,
      "z": -252,
      "magnitude": 5
    },
    {
      "x": -210,
      "y": -21,
      "z": -508,
      "magnitude": 3
    },
    {
      "x": 0,
      "y": -110,
      "z": 756,
      "magnitude": 3
    },
    {
      "x": -508,
      "y": -111,
      "z": 256,
      "magnitude": 3
    },
    {
      "x": 0,
      "y": 0,
      "z": 768,
      "magnitude": 3
    },
    {
      "x": -510,
      "y": -28,
      "z": 267,
      "magnitude": 3
    },
    {
      "x": 15,
      "y": 25,
      "z": -766,
      "magnitude": 3
    },
    {
      "x": 504,
      "y": -594,
      "z": 247,
      "magnitude": 5
    },
    {
      "x": 0,
      "y": -768,
      "z": 768,
      "magnitude": 6
    },
    {
      "x": 5,
      "y": -768,
      "z": -768,
      "magnitude": 6
    },
    {
      "x": 266,
      "y": -285,
      "z": -519,
      "magnitude": 4
    },
    {
      "x": 515,
      "y": -57,
      "z": -263,
      "magnitude": 3
    },
    {
      "x": 254,
      "y": -28,
      "z": 512,
      "magnitude": 3
    },
    {
      "x": 0,
      "y": 0,
      "z": 768,
      "magnitude": 3
    },
    {
      "x": 0,
      "y": -768,
      "z": 768,
      "magnitude": 6
    },
    {
      "x": -6,
      "y": -740,
      "z": -766,
      "magnitude": 6
    },
    {
      "x": -6,
      "y": 0,
      "z": -768,
      "magnitude": 3
    },
    {
      "x": 16,
      "y": 25,
      "z": -766,
      "magnitude": 3
    },
    {
      "x": -254,
      "y": -284,
      "z": 521,
      "magnitude": 4
    },
    {
      "x": -510,
      "y": -512,
      "z": -245,
      "magnitude": 5
    },
    {
      "x": -262,
      "y": 28,
      "z": -510,
      "magnitude": 3
    },
    {
      "x": 0,
      "y": 0,
      "z": 768,
      "magnitude": 3
    },
    {
      "x": -510,
      "y": -28,
      "z": 265,
      "magnitude": 3
    },
    {
      "x": 512,
      "y": -512,
      "z": -256,
      "magnitude": 5
    },
    {
      "x": 256,
      "y": -256,
      "z": 512,
      "magnitude": 4
    },
    {
      "x": -512,
      "y": -512,
      "z": 256,
      "magnitude": 5
    },
    {
      "x": -256,
      "y": -256,
      "z": -512,
      "magnitude": 4
    },
    {
      "x": 256,
      "y": 0,
      "z": -512,
      "magnitude": 3
    },
    {
      "x": 512,
      "y": 0,
      "z": 256,
      "magnitude": 3
    },
    {
      "x": -256,
      "y": 0,
      "z": 512,
      "magnitude": 3
    },
    {
      "x": -512,
      "y": 0,
      "z": -256,
      "magnitude": 3
    },
    {
      "x": 512,
      "y": -512,
      "z": -256,
      "magnitude": 5
    },
    {
      "x": 256,
      "y": -256,
      "z": 512,
      "magnitude": 4
    },
    {
      "x": -512,
      "y": -512,
      "z": 256,
      "magnitude": 5
    },
    {
      "x": -256,
      "y": -256,
      "z": -512,
      "magnitude": 4
    },
    {
      "x": 256,
      "y": 0,
      "z": -512,
      "magnitude": 3
    },
    {
      "x": 512,
      "y": 0,
      "z": 256,
      "magnitude": 3
    },
    {
      "x": -256,
      "y": 0,
      "z": 512,
      "magnitude": 3
    },
    {
      "x": -512,
      "y": 0,
      "z": -256,
      "magnitude": 3
    },
    {
      "x": 512,
      "y": -512,
      "z": -256,
      "magnitude": 5
    },
    {
      "x": 256,
      "y": -256,
      "z": 512,
      "magnitude": 4
    },
    {
      "x": -512,
      "y": -512,
      "z": 256,
      "magnitude": 5
    },
    {
      "x": -256,
      "y": -256,
      "z": -512,
      "magnitude": 4
    },
    {
      "x": 256,
      "y": 0,
      "z": -512,
      "magnitude": 3
    },
    {
      "x": 512,
      "y": 0,
      "z": 256,
      "magnitude": 3
    },
    {
      "x": -256,
      "y": 0,
      "z": 512,
      "magnitude": 3
    },
    {
      "x": -512,
      "y": 0,
      "z": -256,
      "magnitude": 3
    },
    {
      "x": 512,
      "y": -512,
      "z": -256,
      "magnitude": 5
    },
    {
      "x": 256,
      "y": -256,
      "z": 512,
      "magnitude": 4
    },
    {
      "x": -512,
      "y": -512,
      "z": 256,
      "magnitude": 5
    },
    {
      "x": -256,
      "y": -256,
      "z": -512,
      "magnitude": 4
    },
    {
      "x": 256,
      "y": 0,
      "z": -512,
      "magnitude": 3
    },
    {
      "x": 512,
      "y": 0,
      "z": 256,
      "magnitude": 3
    },
    {
      "x": -256,
      "y": 0,
      "z": 512,
      "magnitude": 3
    },
    {
      "x": -512,
      "y": 0,
      "z": -256,
      "magnitude": 3
    },
    {
      "x": 0,
      "y": 0,
      "z": 0,
      "magnitude": 0
    },
    {
      "x": 0,
      "y": 0,
      "z": 0,
      "magnitude": 0
    },
    {
      "x": 0,
      "y": 0,
      "z": 0,
      "magnitude": 0
    },
    {
      "x": 0,
      "y": 0,
      "z": 0,
      "magnitude": 0
    },
    {
      "x": 0,
      "y": 0,
      "z": 0,
      "magnitude": 0
    }
  ],
  "faceCount": 170,
  "faceIndices1": [
    0,
    0,
    0,
    0,
    0,
    0,
    1,
    1,
    1,
    1,
    2,
    2,
    2,
    3,
    3,
    3,
    4,
    4,
    4,
    5,
    5,
    5,
    6,
    6,
    7,
    7,
    7,
    8,
    9,
    9,
    10,
    10,
    10,
    11,
    11,
    12,
    12,
    12,
    19,
    18,
    15,
    16,
    24,
    24,
    24,
    24,
    24,
    25,
    25,
    25,
    25,
    26,
    26,
    26,
    27,
    31,
    31,
    32,
    32,
    38,
    38,
    38,
    38,
    38,
    38,
    39,
    39,
    39,
    40,
    40,
    40,
    41,
    41,
    41,
    49,
    49,
    49,
    53,
    53,
    53,
    53,
    53,
    54,
    54,
    54,
    54,
    55,
    55,
    55,
    49,
    59,
    59,
    60,
    60,
    66,
    59,
    63,
    63,
    64,
    30,
    31,
    35,
    35,
    36,
    44,
    48,
    48,
    51,
    71,
    71,
    71,
    71,
    71,
    72,
    72,
    72,
    72,
    73,
    73,
    73,
    74,
    78,
    78,
    79,
    79,
    77,
    78,
    82,
    82,
    83,
    87,
    87,
    87,
    87,
    87,
    88,
    88,
    89,
    89,
    90,
    95,
    95,
    95,
    95,
    95,
    96,
    96,
    97,
    97,
    98,
    103,
    103,
    103,
    103,
    103,
    104,
    104,
    105,
    105,
    106,
    111,
    111,
    111,
    111,
    111,
    112,
    112,
    113,
    113,
    114
  ],
  "faceIndices2": [
    1,
    2,
    3,
    4,
    5,
    6,
    6,
    7,
    8,
    9,
    9,
    10,
    11,
    11,
    12,
    13,
    13,
    8,
    14,
    14,
    15,
    16,
    16,
    17,
    17,
    18,
    14,
    13,
    13,
    19,
    19,
    20,
    21,
    21,
    22,
    22,
    23,
    19,
    23,
    15,
    18,
    18,
    25,
    26,
    27,
    28,
    29,
    29,
    30,
    31,
    32,
    32,
    33,
    34,
    34,
    35,
    36,
    36,
    37,
    39,
    40,
    41,
    42,
    43,
    44,
    44,
    45,
    46,
    46,
    47,
    48,
    48,
    49,
    50,
    48,
    51,
    52,
    54,
    55,
    49,
    56,
    57,
    57,
    58,
    59,
    60,
    60,
    61,
    62,
    62,
    63,
    64,
    64,
    65,
    59,
    66,
    66,
    67,
    67,
    68,
    68,
    68,
    69,
    69,
    43,
    47,
    70,
    70,
    72,
    73,
    74,
    75,
    76,
    76,
    77,
    78,
    79,
    79,
    80,
    81,
    81,
    82,
    83,
    83,
    84,
    85,
    85,
    85,
    86,
    86,
    88,
    89,
    90,
    91,
    92,
    92,
    93,
    93,
    94,
    94,
    96,
    97,
    98,
    99,
    100,
    100,
    101,
    101,
    102,
    102,
    104,
    105,
    106,
    107,
    108,
    108,
    109,
    109,
    110,
    110,
    112,
    113,
    114,
    115,
    116,
    116,
    117,
    117,
    118,
    118
  ],
  "faceIndices3": [
    2,
    3,
    4,
    5,
    6,
    1,
    7,
    8,
    9,
    2,
    10,
    11,
    3,
    12,
    13,
    4,
    8,
    14,
    5,
    15,
    16,
    6,
    17,
    7,
    18,
    14,
    8,
    9,
    19,
    10,
    20,
    21,
    11,
    22,
    12,
    23,
    19,
    13,
    20,
    14,
    16,
    17,
    26,
    27,
    28,
    29,
    25,
    30,
    31,
    32,
    26,
    33,
    34,
    27,
    28,
    36,
    32,
    37,
    33,
    40,
    41,
    42,
    43,
    44,
    39,
    45,
    46,
    40,
    47,
    48,
    41,
    49,
    50,
    42,
    51,
    52,
    50,
    55,
    49,
    56,
    57,
    54,
    58,
    59,
    60,
    55,
    61,
    62,
    49,
    56,
    64,
    60,
    65,
    61,
    58,
    63,
    67,
    64,
    65,
    31,
    35,
    69,
    36,
    37,
    45,
    70,
    51,
    52,
    73,
    74,
    75,
    76,
    72,
    77,
    78,
    79,
    73,
    80,
    81,
    74,
    75,
    83,
    79,
    84,
    80,
    78,
    82,
    86,
    83,
    84,
    89,
    90,
    91,
    92,
    88,
    93,
    89,
    94,
    90,
    91,
    97,
    98,
    99,
    100,
    96,
    101,
    97,
    102,
    98,
    99,
    105,
    106,
    107,
    108,
    104,
    109,
    105,
    110,
    106,
    107,
    113,
    114,
    115,
    116,
    112,
    117,
    113,
    118,
    114,
    115
  ],
  "faceTransparencies": [
    -112,
    -112,
    -112,
    0,
    0,
    0,
    0,
    0,
    -112,
    -112,
    0,
    0,
    0,
    0,
    0,
    -112,
    -112,
    0,
    0,
    0,
    0,
    0,
    0,
    0,
    0,
    0,
    0,
    -112,
    0,
    0,
    0,
    0,
    0,
    0,
    0,
    0,
    0,
    0,
    0,
    0,
    0,
    0,
    0,
    0,
    0,
    0,
    0,
    0,
    0,
    0,
    0,
    0,
    0,
    0,
    0,
    0,
    0,
    0,
    0,
    0,
    0,
    0,
    0,
    0,
    0,
    0,
    0,
    0,
    0,
    0,
    0,
    0,
    0,
    0,
    0,
    0,
    0,
    0,
    0,
    0,
    0,
    0,
    0,
    0,
    0,
    0,
    0,
    0,
    0,
    0,
    0,
    0,
    0,
    0,
    0,
    0,
    0,
    0,
    0,
    0,
    0,
    0,
    0,
    0,
    0,
    0,
    0,
    0,
    0,
    0,
    0,
    0,
    0,
    0,
    0,
    0,
    0,
    0,
    0,
    0,
    0,
    0,
    0,
    0,
    0,
    0,
    0,
    0,
    0,
    0,
    0,
    0,
    0,
    0,
    0,
    0,
    0,
    0,
    0,
    0,
    0,
    0,
    0,
    0,
    0,
    0,
    0,
    0,
    0,
    0,
    0,
    0,
    0,
    0,
    0,
    0,
    0,
    0,
    0,
    0,
    0,
    0,
    0,
    0,
    0,
    0,
    0,
    0,
    0,
    0
  ],
  "faceColors": [
    61,
    61,
    61,
    6323,
    6323,
    6323,
    6323,
    6323,
    61,
    61,
    6323,
    6323,
    6323,
    6323,
    6323,
    61,
    61,
    6323,
    6323,
    6323,
    6323,
    6323,
    6323,
    6323,
    6323,
    6323,
    6323,
    61,
    6323,
    6323,
    6323,
    6323,
    6323,
    6323,
    6323,
    6323,
    6323,
    6323,
    6323,
    6323,
    6323,
    6323,
    5665,
    5665,
    5532,
    5532,
    5656,
    5656,
    5656,
    5665,
    5665,
    5656,
    5656,
    5656,
    5656,
    5665,
    5665,
    5656,
    5656,
    5665,
    5665,
    5656,
    5656,
    5656,
    5665,
    5532,
    5532,
    5656,
    5656,
    5656,
    5665,
    5665,
    5656,
    5656,
    5665,
    5532,
    5532,
    5665,
    5665,
    5532,
    5532,
    5656,
    5656,
    5656,
    5665,
    5665,
    5656,
    5656,
    5656,
    5656,
    5665,
    5665,
    5656,
    5656,
    5656,
    5656,
    5656,
    5532,
    5532,
    5656,
    5656,
    5656,
    5532,
    5532,
    5656,
    5656,
    5656,
    5656,
    5665,
    5665,
    5532,
    5532,
    5656,
    5656,
    5656,
    5665,
    5665,
    5656,
    5656,
    5656,
    5656,
    5665,
    5665,
    5656,
    5656,
    5656,
    5656,
    5656,
    5532,
    5532,
    5656,
    5656,
    5656,
    5656,
    5656,
    5656,
    5656,
    5656,
    5656,
    5656,
    5656,
    5656,
    5656,
    5656,
    5656,
    5656,
    5656,
    5656,
    5656,
    5656,
    5656,
    5656,
    5656,
    5656,
    5656,
    5656,
    5656,
    5656,
    5656,
    5656,
    5656,
    5656,
    5656,
    5656,
    5656,
    5656,
    5656,
    5656,
    5656,
    5656
  ],
  "faceRenderPriorities": [
    2,
    2,
    2,
    2,
    2,
    2,
    2,
    2,
    2,
    2,
    2,
    2,
    2,
    2,
    2,
    2,
    2,
    2,
    2,
    2,
    2,
    2,
    2,
    2,
    2,
    2,
    2,
    2,
    2,
    2,
    2,
    2,
    2,
    2,
    2,
    2,
    2,
    2,
    2,
    2,
    2,
    2,
    1,
    1,
    0,
    0,
    0,
    0,
    0,
    1,
    1,
    0,
    0,
    0,
    0,
    1,
    1,
    0,
    0,
    1,
    1,
    0,
    0,
    0,
    1,
    0,
    0,
    0,
    0,
    0,
    1,
    1,
    0,
    0,
    1,
    0,
    0,
    1,
    1,
    0,
    0,
    0,
    0,
    0,
    1,
    1,
    0,
    0,
    0,
    0,
    1,
    1,
    0,
    0,
    0,
    0,
    0,
    0,
    0,
    0,
    0,
    0,
    0,
    0,
    0,
    0,
    0,
    0,
    1,
    1,
    0,
    0,
    0,
    0,
    0,
    1,
    1,
    0,
    0,
    0,
    0,
    1,
    1,
    0,
    0,
    0,
    0,
    0,
    0,
    0,
    0,
    0,
    0,
    0,
    0,
    0,
    0,
    0,
    0,
    0,
    0,
    0,
    0,
    0,
    0,
    0,
    0,
    0,
    0,
    0,
    0,
    0,
    0,
    0,
    0,
    0,
    0,
    0,
    0,
    0,
    0,
    0,
    0,
    0,
    0,
    0,
    0,
    0,
    0,
    0
  ],
  "numTextureFaces": 0,
  "faceTextureUCoordinates": [
    null,
    null,
    null,
    null,
    null,
    null,
    null,
    null,
    null,
    null,
    null,
    null,
    null,
    null,
    null,
    null,
    null,
    null,
    null,
    null,
    null,
    null,
    null,
    null,
    null,
    null,
    null,
    null,
    null,
    null,
    null,
    null,
    null,
    null,
    null,
    null,
    null,
    null,
    null,
    null,
    null,
    null,
    null,
    null,
    null,
    null,
    null,
    null,
    null,
    null,
    null,
    null,
    null,
    null,
    null,
    null,
    null,
    null,
    null,
    null,
    null,
    null,
    null,
    null,
    null,
    null,
    null,
    null,
    null,
    null,
    null,
    null,
    null,
    null,
    null,
    null,
    null,
    null,
    null,
    null,
    null,
    null,
    null,
    null,
    null,
    null,
    null,
    null,
    null,
    null,
    null,
    null,
    null,
    null,
    null,
    null,
    null,
    null,
    null,
    null,
    null,
    null,
    null,
    null,
    null,
    null,
    null,
    null,
    null,
    null,
    null,
    null,
    null,
    null,
    null,
    null,
    null,
    null,
    null,
    null,
    null,
    null,
    null,
    null,
    null,
    null,
    null,
    null,
    null,
    null,
    null,
    null,
    null,
    null,
    null,
    null,
    null,
    null,
    null,
    null,
    null,
    null,
    null,
    null,
    null,
    null,
    null,
    null,
    null,
    null,
    null,
    null,
    null,
    null,
    null,
    null,
    null,
    null,
    null,
    null,
    null,
    null,
    null,
    null,
    null,
    null,
    null,
    null,
    null,
    null
  ],
  "faceTextureVCoordinates": [
    null,
    null,
    null,
    null,
    null,
    null,
    null,
    null,
    null,
    null,
    null,
    null,
    null,
    null,
    null,
    null,
    null,
    null,
    null,
    null,
    null,
    null,
    null,
    null,
    null,
    null,
    null,
    null,
    null,
    null,
    null,
    null,
    null,
    null,
    null,
    null,
    null,
    null,
    null,
    null,
    null,
    null,
    null,
    null,
    null,
    null,
    null,
    null,
    null,
    null,
    null,
    null,
    null,
    null,
    null,
    null,
    null,
    null,
    null,
    null,
    null,
    null,
    null,
    null,
    null,
    null,
    null,
    null,
    null,
    null,
    null,
    null,
    null,
    null,
    null,
    null,
    null,
    null,
    null,
    null,
    null,
    null,
    null,
    null,
    null,
    null,
    null,
    null,
    null,
    null,
    null,
    null,
    null,
    null,
    null,
    null,
    null,
    null,
    null,
    null,
    null,
    null,
    null,
    null,
    null,
    null,
    null,
    null,
    null,
    null,
    null,
    null,
    null,
    null,
    null,
    null,
    null,
    null,
    null,
    null,
    null,
    null,
    null,
    null,
    null,
    null,
    null,
    null,
    null,
    null,
    null,
    null,
    null,
    null,
    null,
    null,
    null,
    null,
    null,
    null,
    null,
    null,
    null,
    null,
    null,
    null,
    null,
    null,
    null,
    null,
    null,
    null,
    null,
    null,
    null,
    null,
    null,
    null,
    null,
    null,
    null,
    null,
    null,
    null,
    null,
    null,
    null,
    null,
    null,
    null
  ],
  "priority": 0,
  "maxPriority": 0
}