{
  "id": 995,
  "vertexCount": 5,
  "vertexX": [
    -64,
    -64,
    -56,
    -56,
    -64
  ],
  "vertexY": [
    -72,
    -55,
    -55,
    -72,
    -70
  ],
  "vertexZ": [
    56,
    56,
    64,
    64,
    64
  ],
  "vertexNormals": [
    {
      "x": 301,
      "y": -244,
      "z": -301,
      "magnitude": 3
    },
    {
      "x": 181,
      "y": 0,
      "z": -181,
      "magnitude": 1
    },
    {
      "x": 362,
      "y": 0,
      "z": -362,
      "magnitude": 2
    },
    {
      "x": 120,
      "y": -244,
      "z": -120,
      "magnitude": 2
    },
    {
      "x": -61,
      "y": -244,
      "z": 61,
      "magnitude": 1
    }
  ],
  "faceCount": 3,
  "faceIndices1": [
    0,
    0,
    0
  ],
  "faceIndices2": [
    1,
    2,
    3
  ],
  "faceIndices3": [
    2,
    3,
    4
  ],
  "faceColors": [
    6932,
    6932,
    6684
  ],
  "numTextureFaces": 0,
  "faceTextureUCoordinates": [
    null,
    null,
    null
  ],
  "faceTextureVCoordinates": [
    null,
    null,
    null
  ],
  "priority": 1,
  "maxPriority": 0
}